personalization/__init__.py
personalization/__main__.py
personalization/abstract_pipeline.py
personalization/file_utils.py
personalization/ranking_pipeline.py
personalization-0.1.1.dist-info/LICENSE
personalization-0.1.1.dist-info/WHEEL
personalization-0.1.1.dist-info/METADATA
personalization-0.1.1.dist-info/RECORD
