Metadata-Version: 2.1
Name: personalization
Version: 0.1.1
Summary: An end-to-end machine learning pipeline to train ml model and deploy it to realtime inference endpoint
License: MIT
Author: Rauan Akylzhanov
Author-email: akylzhanov.r@gmail.com
Requires-Python: >=3.8.1,<4.0
Classifier: License :: OSI Approved :: MIT License
Classifier: Programming Language :: Python :: 3
Classifier: Programming Language :: Python :: 3.9
Classifier: Programming Language :: Python :: 3.10
Classifier: Programming Language :: Python :: 3.11
Requires-Dist: lightgbm (>=3.3.5,<4.0.0)
Requires-Dist: pandas (>=1.5.3,<2.0.0)
Requires-Dist: polars (>=0.16.6,<0.17.0)
Requires-Dist: pyarrow (>=11.0.0,<12.0.0)
Requires-Dist: scikit-learn (>=1.2.1,<2.0.0)
Requires-Dist: twine (>=4.0.2,<5.0.0)
